src/common/counter.v
// ************************************************************
// Engineer: kaikai
//
// Create Date: 2024/04/05
// Design Name: ConvCode
// Module Name: counter.v
// Tool versions: VsCode
// Description: 计数器
// Parameter:
// 1. NUM: 计数器的最大值
// Input:
// 1. clk_sig: 时钟信号
// 2. reset_sig: 复位信号
// Output:
// 1. counter_sig: 计数器的值
// Notice:
// 1. 计数器的值从 0 开始
// ************************************************************
module counter #(
    parameter NUM = 11'b111_1111_1111
) (
    input                            clk_sig,
    input                            reset_sig,   // 复位信号 低电平有效
    output reg [($clog2(NUM) - 1):0] counter_sig  // 计数器的值
);
    initial begin
        counter_sig <= 0;
    end

    always @(posedge clk_sig) begin
        if (!reset_sig || counter_sig == NUM) begin
            counter_sig <= 0;
        end else begin
            counter_sig <= counter_sig + 1;
        end
    end
endmodule

test/counter_tb.v
//~ `New testbench
`timescale 1ns / 1ps

module counter_tb;

    // counter Parameters
    parameter PERIOD = 50;
    parameter NUM = 11'b111_1111_1111;
    parameter LEN = 11;

    // counter Inputs
    reg                clk_sig = 0;
    reg                reset_sig = 0;

    // counter Outputs
    wire [(LEN - 1):0] counter_sig;

    /*iverilog */
    initial begin
        $dumpfile("counter.vcd");  //生成的vcd文件名称
        $dumpvars(0, counter_tb);  //tb模块名称
    end
    /*iverilog */

    always begin
        #(PERIOD / 2) clk_sig = ~clk_sig;
    end

    initial begin
        #(PERIOD * 2) reset_sig = 1;
    end

    counter #(
        .NUM(NUM)
    ) u_counter (
        .clk_sig  (clk_sig),
        .reset_sig(reset_sig),

        .counter_sig(counter_sig[(LEN-1):0])
    );

    initial begin
        #(PERIOD * NUM * 2) $finish;
    end
endmodule

simulation/vcd/counter.vcd
$date
	Fri Apr  5 22:57:02 2024
$end
$version
	Icarus Verilog
$end
$timescale
	1ps
$end
$scope module counter_tb $end
$var wire 11 ! counter_sig [10:0] $end
$var parameter 32 " LEN $end
$var parameter 11 # NUM $end
$var parameter 32 $ PERIOD $end
$var reg 1 % clk_sig $end
$var reg 1 & reset_sig $end
$scope module u_counter $end
$var wire 1 % clk_sig $end
$var wire 1 & reset_sig $end
$var parameter 11 ' NUM $end
$var reg 11 ( counter_sig [10:0] $end
$upscope $end
$upscope $end
$enddefinitions $end
$comment Show the parameter values. $end
$dumpall
b11111111111 '
b110010 $
b11111111111 #
b1011 "
$end
#0
$dumpvars
b0 (
0&
0%
b0 !
$end
#25000
1%
#50000
0%
#75000
1%
#100000
0%
1&
#125000
b1 !
b1 (
1%
#150000
0%
#175000
b10 !
b10 (
1%
#200000
0%
#225000
b11 !
b11 (
1%
#250000
0%
#275000
b100 !
b100 (
1%
#300000
0%
#325000
b101 !
b101 (
1%
#350000
0%
#375000
b110 !
b110 (
1%
#400000
0%
#425000
b111 !
b111 (
1%
#450000
0%
#475000
b1000 !
b1000 (
1%
#500000
0%
#525000
b1001 !
b1001 (
1%
#550000
0%
#575000
b1010 !
b1010 (
1%
#600000
0%
#625000
b1011 !
b1011 (
1%
#650000
0%
#675000
b1100 !
b1100 (
1%
#700000
0%
#725000
b1101 !
b1101 (
1%
#750000
0%
#775000
b1110 !
b1110 (
1%
#800000
0%
#825000
b1111 !
b1111 (
1%
#850000
0%
#875000
b10000 !
b10000 (
1%
#900000
0%
#925000
b10001 !
b10001 (
1%
#950000
0%
#975000
b10010 !
b10010 (
1%
#1000000
0%
#1025000
b10011 !
b10011 (
1%
#1050000
0%
#1075000
b10100 !
b10100 (
1%
#1100000
0%
#1125000
b10101 !
b10101 (
1%
#1150000
0%
#1175000
b10110 !
b10110 (
1%
#1200000
0%
#1225000
b10111 !
b10111 (
1%
#1250000
0%
#1275000
b11000 !
b11000 (
1%
#1300000
0%
#1325000
b11001 !
b11001 (
1%
#1350000
0%
#1375000
b11010 !
b11010 (
1%
#1400000
0%
#1425000
b11011 !
b11011 (
1%
#1450000
0%
#1475000
b11100 !
b11100 (
1%
#1500000
0%
#1525000
b11101 !
b11101 (
1%
#1550000
0%
#1575000
b11110 !
b11110 (
1%
#1600000
0%
#1625000
b11111 !
b11111 (
1%
#1650000
0%
#1675000
b100000 !
b100000 (
1%
#1700000
0%
#1725000
b100001 !
b100001 (
1%
#1750000
0%
#1775000
b100010 !
b100010 (
1%
#1800000
0%
#1825000
b100011 !
b100011 (
1%
#1850000
0%
#1875000
b100100 !
b100100 (
1%
#1900000
0%
#1925000
b100101 !
b100101 (
1%
#1950000
0%
#1975000
b100110 !
b100110 (
1%
#2000000
0%
#2025000
b100111 !
b100111 (
1%
#2050000
0%
#2075000
b101000 !
b101000 (
1%
#2100000
0%
#2125000
b101001 !
b101001 (
1%
#2150000
0%
#2175000
b101010 !
b101010 (
1%
#2200000
0%
#2225000
b101011 !
b101011 (
1%
#2250000
0%
#2275000
b101100 !
b101100 (
1%
#2300000
0%
#2325000
b101101 !
b101101 (
1%
#2350000
0%
#2375000
b101110 !
b101110 (
1%
#2400000
0%
#2425000
b101111 !
b101111 (
1%
#2450000
0%
#2475000
b110000 !
b110000 (
1%
#2500000
0%
#2525000
b110001 !
b110001 (
1%
#2550000
0%
#2575000
b110010 !
b110010 (
1%
#2600000
0%
#2625000
b110011 !
b110011 (
1%
#2650000
0%
#2675000
b110100 !
b110100 (
1%
#2700000
0%
#2725000
b110101 !
b110101 (
1%
#2750000
0%
#2775000
b110110 !
b110110 (
1%
#2800000
0%
#2825000
b110111 !
b110111 (
1%
#2850000
0%
#2875000
b111000 !
b111000 (
1%
#2900000
0%
#2925000
b111001 !
b111001 (
1%
#2950000
0%
#2975000
b111010 !
b111010 (
1%
#3000000
0%
#3025000
b111011 !
b111011 (
1%
#3050000
0%
#3075000
b111100 !
b111100 (
1%
#3100000
0%
#3125000
b111101 !
b111101 (
1%
#3150000
0%
#3175000
b111110 !
b111110 (
1%
#3200000
0%
#3225000
b111111 !
b111111 (
1%
#3250000
0%
#3275000
b1000000 !
b1000000 (
1%
#3300000
0%
#3325000
b1000001 !
b1000001 (
1%
#3350000
0%
#3375000
b1000010 !
b1000010 (
1%
#3400000
0%
#3425000
b1000011 !
b1000011 (
1%
#3450000
0%
#3475000
b1000100 !
b1000100 (
1%
#3500000
0%
#3525000
b1000101 !
b1000101 (
1%
#3550000
0%
#3575000
b1000110 !
b1000110 (
1%
#3600000
0%
#3625000
b1000111 !
b1000111 (
1%
#3650000
0%
#3675000
b1001000 !
b1001000 (
1%
#3700000
0%
#3725000
b1001001 !
b1001001 (
1%
#3750000
0%
#3775000
b1001010 !
b1001010 (
1%
#3800000
0%
#3825000
b1001011 !
b1001011 (
1%
#3850000
0%
#3875000
b1001100 !
b1001100 (
1%
#3900000
0%
#3925000
b1001101 !
b1001101 (
1%
#3950000
0%
#3975000
b1001110 !
b1001110 (
1%
#4000000
0%
#4025000
b1001111 !
b1001111 (
1%
#4050000
0%
#4075000
b1010000 !
b1010000 (
1%
#4100000
0%
#4125000
b1010001 !
b1010001 (
1%
#4150000
0%
#4175000
b1010010 !
b1010010 (
1%
#4200000
0%
#4225000
b1010011 !
b1010011 (
1%
#4250000
0%
#4275000
b1010100 !
b1010100 (
1%
#4300000
0%
#4325000
b1010101 !
b1010101 (
1%
#4350000
0%
#4375000
b1010110 !
b1010110 (
1%
#4400000
0%
#4425000
b1010111 !
b1010111 (
1%
#4450000
0%
#4475000
b1011000 !
b1011000 (
1%
#4500000
0%
#4525000
b1011001 !
b1011001 (
1%
#4550000
0%
#4575000
b1011010 !
b1011010 (
1%
#4600000
0%
#4625000
b1011011 !
b1011011 (
1%
#4650000
0%
#4675000
b1011100 !
b1011100 (
1%
#4700000
0%
#4725000
b1011101 !
b1011101 (
1%
#4750000
0%
#4775000
b1011110 !
b1011110 (
1%
#4800000
0%
#4825000
b1011111 !
b1011111 (
1%
#4850000
0%
#4875000
b1100000 !
b1100000 (
1%
#4900000
0%
#4925000
b1100001 !
b1100001 (
1%
#4950000
0%
#4975000
b1100010 !
b1100010 (
1%
#5000000
0%
#5025000
b1100011 !
b1100011 (
1%
#5050000
0%
#5075000
b1100100 !
b1100100 (
1%
#5100000
0%
#5125000
b1100101 !
b1100101 (
1%
#5150000
0%
#5175000
b1100110 !
b1100110 (
1%
#5200000
0%
#5225000
b1100111 !
b1100111 (
1%
#5250000
0%
#5275000
b1101000 !
b1101000 (
1%
#5300000
0%
#5325000
b1101001 !
b1101001 (
1%
#5350000
0%
#5375000
b1101010 !
b1101010 (
1%
#5400000
0%
#5425000
b1101011 !
b1101011 (
1%
#5450000
0%
#5475000
b1101100 !
b1101100 (
1%
#5500000
0%
#5525000
b1101101 !
b1101101 (
1%
#5550000
0%
#5575000
b1101110 !
b1101110 (
1%
#5600000
0%
#5625000
b1101111 !
b1101111 (
1%
#5650000
0%
#5675000
b1110000 !
b1110000 (
1%
#5700000
0%
#5725000
b1110001 !
b1110001 (
1%
#5750000
0%
#5775000
b1110010 !
b1110010 (
1%
#5800000
0%
#5825000
b1110011 !
b1110011 (
1%
#5850000
0%
#5875000
b1110100 !
b1110100 (
1%
#5900000
0%
#5925000
b1110101 !
b1110101 (
1%
#5950000
0%
#5975000
b1110110 !
b1110110 (
1%
#6000000
0%
#6025000
b1110111 !
b1110111 (
1%
#6050000
0%
#6075000
b1111000 !
b1111000 (
1%
#6100000
0%
#6125000
b1111001 !
b1111001 (
1%
#6150000
0%
#6175000
b1111010 !
b1111010 (
1%
#6200000
0%
#6225000
b1111011 !
b1111011 (
1%
#6250000
0%
#6275000
b1111100 !
b1111100 (
1%
#6300000
0%
#6325000
b1111101 !
b1111101 (
1%
#6350000
0%
#6375000
b1111110 !
b1111110 (
1%
#6400000
0%
#6425000
b1111111 !
b1111111 (
1%
#6450000
0%
#6475000
b10000000 !
b10000000 (
1%
#6500000
0%
#6525000
b10000001 !
b10000001 (
1%
#6550000
0%
#6575000
b10000010 !
b10000010 (
1%
#6600000
0%
#6625000
b10000011 !
b10000011 (
1%
#6650000
0%
#6675000
b10000100 !
b10000100 (
1%
#6700000
0%
#6725000
b10000101 !
b10000101 (
1%
#6750000
0%
#6775000
b10000110 !
b10000110 (
1%
#6800000
0%
#6825000
b10000111 !
b10000111 (
1%
#6850000
0%
#6875000
b10001000 !
b10001000 (
1%
#6900000
0%
#6925000
b10001001 !
b10001001 (
1%
#6950000
0%
#6975000
b10001010 !
b10001010 (
1%
#7000000
0%
#7025000
b10001011 !
b10001011 (
1%
#7050000
0%
#7075000
b10001100 !
b10001100 (
1%
#7100000
0%
#7125000
b10001101 !
b10001101 (
1%
#7150000
0%
#7175000
b10001110 !
b10001110 (
1%
#7200000
0%
#7225000
b10001111 !
b10001111 (
1%
#7250000
0%
#7275000
b10010000 !
b10010000 (
1%
#7300000
0%
#7325000
b10010001 !
b10010001 (
1%
#7350000
0%
#7375000
b10010010 !
b10010010 (
1%
#7400000
0%
#7425000
b10010011 !
b10010011 (
1%
#7450000
0%
#7475000
b10010100 !
b10010100 (
1%
#7500000
0%
#7525000
b10010101 !
b10010101 (
1%
#7550000
0%
#7575000
b10010110 !
b10010110 (
1%
#7600000
0%
#7625000
b10010111 !
b10010111 (
1%
#7650000
0%
#7675000
b10011000 !
b10011000 (
1%
#7700000
0%
#7725000
b10011001 !
b10011001 (
1%
#7750000
0%
#7775000
b10011010 !
b10011010 (
1%
#7800000
0%
#7825000
b10011011 !
b10011011 (
1%
#7850000
0%
#7875000
b10011100 !
b10011100 (
1%
#7900000
0%
#7925000
b10011101 !
b10011101 (
1%
#7950000
0%
#7975000
b10011110 !
b10011110 (
1%
#8000000
0%
#8025000
b10011111 !
b10011111 (
1%
#8050000
0%
#8075000
b10100000 !
b10100000 (
1%
#8100000
0%
#8125000
b10100001 !
b10100001 (
1%
#8150000
0%
#8175000
b10100010 !
b10100010 (
1%
#8200000
0%
#8225000
b10100011 !
b10100011 (
1%
#8250000
0%
#8275000
b10100100 !
b10100100 (
1%
#8300000
0%
#8325000
b10100101 !
b10100101 (
1%
#8350000
0%
#8375000
b10100110 !
b10100110 (
1%
#8400000
0%
#8425000
b10100111 !
b10100111 (
1%
#8450000
0%
#8475000
b10101000 !
b10101000 (
1%
#8500000
0%
#8525000
b10101001 !
b10101001 (
1%
#8550000
0%
#8575000
b10101010 !
b10101010 (
1%
#8600000
0%
#8625000
b10101011 !
b10101011 (
1%
#8650000
0%
#8675000
b10101100 !
b10101100 (
1%
#8700000
0%
#8725000
b10101101 !
b10101101 (
1%
#8750000
0%
#8775000
b10101110 !
b10101110 (
1%
#8800000
0%
#8825000
b10101111 !
b10101111 (
1%
#8850000
0%
#8875000
b10110000 !
b10110000 (
1%
#8900000
0%
#8925000
b10110001 !
b10110001 (
1%
#8950000
0%
#8975000
b10110010 !
b10110010 (
1%
#9000000
0%
#9025000
b10110011 !
b10110011 (
1%
#9050000
0%
#9075000
b10110100 !
b10110100 (
1%
#9100000
0%
#9125000
b10110101 !
b10110101 (
1%
#9150000
0%
#9175000
b10110110 !
b10110110 (
1%
#9200000
0%
#9225000
b10110111 !
b10110111 (
1%
#9250000
0%
#9275000
b10111000 !
b10111000 (
1%
#9300000
0%
#9325000
b10111001 !
b10111001 (
1%
#9350000
0%
#9375000
b10111010 !
b10111010 (
1%
#9400000
0%
#9425000
b10111011 !
b10111011 (
1%
#9450000
0%
#9475000
b10111100 !
b10111100 (
1%
#9500000
0%
#9525000
b10111101 !
b10111101 (
1%
#9550000
0%
#9575000
b10111110 !
b10111110 (
1%
#9600000
0%
#9625000
b10111111 !
b10111111 (
1%
#9650000
0%
#9675000
b11000000 !
b11000000 (
1%
#9700000
0%
#9725000
b11000001 !
b11000001 (
1%
#9750000
0%
#9775000
b11000010 !
b11000010 (
1%
#9800000
0%
#9825000
b11000011 !
b11000011 (
1%
#9850000
0%
#9875000
b11000100 !
b11000100 (
1%
#9900000
0%
#9925000
b11000101 !
b11000101 (
1%
#9950000
0%
#9975000
b11000110 !
b11000110 (
1%
#10000000
0%
#10025000
b11000111 !
b11000111 (
1%
#10050000
0%
#10075000
b11001000 !
b11001000 (
1%
#10100000
0%
#10125000
b11001001 !
b11001001 (
1%
#10150000
0%
#10175000
b11001010 !
b11001010 (
1%
#10200000
0%
#10225000
b11001011 !
b11001011 (
1%
#10250000
0%
#10275000
b11001100 !
b11001100 (
1%
#10300000
0%
#10325000
b11001101 !
b11001101 (
1%
#10350000
0%
#10375000
b11001110 !
b11001110 (
1%
#10400000
0%
#10425000
b11001111 !
b11001111 (
1%
#10450000
0%
#10475000
b11010000 !
b11010000 (
1%
#10500000
0%
#10525000
b11010001 !
b11010001 (
1%
#10550000
0%
#10575000
b11010010 !
b11010010 (
1%
#10600000
0%
#10625000
b11010011 !
b11010011 (
1%
#10650000
0%
#10675000
b11010100 !
b11010100 (
1%
#10700000
0%
#10725000
b11010101 !
b11010101 (
1%
#10750000
0%
#10775000
b11010110 !
b11010110 (
1%
#10800000
0%
#10825000
b11010111 !
b11010111 (
1%
#10850000
0%
#10875000
b11011000 !
b11011000 (
1%
#10900000
0%
#10925000
b11011001 !
b11011001 (
1%
#10950000
0%
#10975000
b11011010 !
b11011010 (
1%
#11000000
0%
#11025000
b11011011 !
b11011011 (
1%
#11050000
0%
#11075000
b11011100 !
b11011100 (
1%
#11100000
0%
#11125000
b11011101 !
b11011101 (
1%
#11150000
0%
#11175000
b11011110 !
b11011110 (
1%
#11200000
0%
#11225000
b11011111 !
b11011111 (
1%
#11250000
0%
#11275000
b11100000 !
b11100000 (
1%
#11300000
0%
#11325000
b11100001 !
b11100001 (
1%
#11350000
0%
#11375000
b11100010 !
b11100010 (
1%
#11400000
0%
#11425000
b11100011 !
b11100011 (
1%
#11450000
0%
#11475000
b11100100 !
b11100100 (
1%
#11500000
0%
#11525000
b11100101 !
b11100101 (
1%
#11550000
0%
#11575000
b11100110 !
b11100110 (
1%
#11600000
0%
#11625000
b11100111 !
b11100111 (
1%
#11650000
0%
#11675000
b11101000 !
b11101000 (
1%
#11700000
0%
#11725000
b11101001 !
b11101001 (
1%
#11750000
0%
#11775000
b11101010 !
b11101010 (
1%
#11800000
0%
#11825000
b11101011 !
b11101011 (
1%
#11850000
0%
#11875000
b11101100 !
b11101100 (
1%
#11900000
0%
#11925000
b11101101 !
b11101101 (
1%
#11950000
0%
#11975000
b11101110 !
b11101110 (
1%
#12000000
0%
#12025000
b11101111 !
b11101111 (
1%
#12050000
0%
#12075000
b11110000 !
b11110000 (
1%
#12100000
0%
#12125000
b11110001 !
b11110001 (
1%
#12150000
0%
#12175000
b11110010 !
b11110010 (
1%
#12200000
0%
#12225000
b11110011 !
b11110011 (
1%
#12250000
0%
#12275000
b11110100 !
b11110100 (
1%
#12300000
0%
#12325000
b11110101 !
b11110101 (
1%
#12350000
0%
#12375000
b11110110 !
b11110110 (
1%
#12400000
0%
#12425000
b11110111 !
b11110111 (
1%
#12450000
0%
#12475000
b11111000 !
b11111000 (
1%
#12500000
0%
#12525000
b11111001 !
b11111001 (
1%
#12550000
0%
#12575000
b11111010 !
b11111010 (
1%
#12600000
0%
#12625000
b11111011 !
b11111011 (
1%
#12650000
0%
#12675000
b11111100 !
b11111100 (
1%
#12700000
0%
#12725000
b11111101 !
b11111101 (
1%
#12750000
0%
#12775000
b11111110 !
b11111110 (
1%
#12800000
0%
#12825000
b11111111 !
b11111111 (
1%
#12850000
0%
#12875000
b100000000 !
b100000000 (
1%
#12900000
0%
#12925000
b100000001 !
b100000001 (
1%
#12950000
0%
#12975000
b100000010 !
b100000010 (
1%
#13000000
0%
#13025000
b100000011 !
b100000011 (
1%
#13050000
0%
#13075000
b100000100 !
b100000100 (
1%
#13100000
0%
#13125000
b100000101 !
b100000101 (
1%
#13150000
0%
#13175000
b100000110 !
b100000110 (
1%
#13200000
0%
#13225000
b100000111 !
b100000111 (
1%
#13250000
0%
#13275000
b100001000 !
b100001000 (
1%
#13300000
0%
#13325000
b100001001 !
b100001001 (
1%
#13350000
0%
#13375000
b100001010 !
b100001010 (
1%
#13400000
0%
#13425000
b100001011 !
b100001011 (
1%
#13450000
0%
#13475000
b100001100 !
b100001100 (
1%
#13500000
0%
#13525000
b100001101 !
b100001101 (
1%
#13550000
0%
#13575000
b100001110 !
b100001110 (
1%
#13600000
0%
#13625000
b100001111 !
b100001111 (
1%
#13650000
0%
#13675000
b100010000 !
b100010000 (
1%
#13700000
0%
#13725000
b100010001 !
b100010001 (
1%
#13750000
0%
#13775000
b100010010 !
b100010010 (
1%
#13800000
0%
#13825000
b100010011 !
b100010011 (
1%
#13850000
0%
#13875000
b100010100 !
b100010100 (
1%
#13900000
0%
#13925000
b100010101 !
b100010101 (
1%
#13950000
0%
#13975000
b100010110 !
b100010110 (
1%
#14000000
0%
#14025000
b100010111 !
b100010111 (
1%
#14050000
0%
#14075000
b100011000 !
b100011000 (
1%
#14100000
0%
#14125000
b100011001 !
b100011001 (
1%
#14150000
0%
#14175000
b100011010 !
b100011010 (
1%
#14200000
0%
#14225000
b100011011 !
b100011011 (
1%
#14250000
0%
#14275000
b100011100 !
b100011100 (
1%
#14300000
0%
#14325000
b100011101 !
b100011101 (
1%
#14350000
0%
#14375000
b100011110 !
b100011110 (
1%
#14400000
0%
#14425000
b100011111 !
b100011111 (
1%
#14450000
0%
#14475000
b100100000 !
b100100000 (
1%
#14500000
0%
#14525000
b100100001 !
b100100001 (
1%
#14550000
0%
#14575000
b100100010 !
b100100010 (
1%
#14600000
0%
#14625000
b100100011 !
b100100011 (
1%
#14650000
0%
#14675000
b100100100 !
b100100100 (
1%
#14700000
0%
#14725000
b100100101 !
b100100101 (
1%
#14750000
0%
#14775000
b100100110 !
b100100110 (
1%
#14800000
0%
#14825000
b100100111 !
b100100111 (
1%
#14850000
0%
#14875000
b100101000 !
b100101000 (
1%
#14900000
0%
#14925000
b100101001 !
b100101001 (
1%
#14950000
0%
#14975000
b100101010 !
b100101010 (
1%
#15000000
0%
#15025000
b100101011 !
b100101011 (
1%
#15050000
0%
#15075000
b100101100 !
b100101100 (
1%
#15100000
0%
#15125000
b100101101 !
b100101101 (
1%
#15150000
0%
#15175000
b100101110 !
b100101110 (
1%
#15200000
0%
#15225000
b100101111 !
b100101111 (
1%
#15250000
0%
#15275000
b100110000 !
b100110000 (
1%
#15300000
0%
#15325000
b100110001 !
b100110001 (
1%
#15350000
0%
#15375000
b100110010 !
b100110010 (
1%
#15400000
0%
#15425000
b100110011 !
b100110011 (
1%
#15450000
0%
#15475000
b100110100 !
b100110100 (
1%
#15500000
0%
#15525000
b100110101 !
b100110101 (
1%
#15550000
0%
#15575000
b100110110 !
b100110110 (
1%
#15600000
0%
#15625000
b100110111 !
b100110111 (
1%
#15650000
0%
#15675000
b100111000 !
b100111000 (
1%
#15700000
0%
#15725000
b100111001 !
b100111001 (
1%
#15750000
0%
#15775000
b100111010 !
b100111010 (
1%
#15800000
0%
#15825000
b100111011 !
b100111011 (
1%
#15850000
0%
#15875000
b100111100 !
b100111100 (
1%
#15900000
0%
#15925000
b100111101 !
b100111101 (
1%
#15950000
0%
#15975000
b100111110 !
b100111110 (
1%
#16000000
0%
#16025000
b100111111 !
b100111111 (
1%
#16050000
0%
#16075000
b101000000 !
b101000000 (
1%
#16100000
0%
#16125000
b101000001 !
b101000001 (
1%
#16150000
0%
#16175000
b101000010 !
b101000010 (
1%
#16200000
0%
#16225000
b101000011 !
b101000011 (
1%
#16250000
0%
#16275000
b101000100 !
b101000100 (
1%
#16300000
0%
#16325000
b101000101 !
b101000101 (
1%
#16350000
0%
#16375000
b101000110 !
b101000110 (
1%
#16400000
0%
#16425000
b101000111 !
b101000111 (
1%
#16450000
0%
#16475000
b101001000 !
b101001000 (
1%
#16500000
0%
#16525000
b101001001 !
b101001001 (
1%
#16550000
0%
#16575000
b101001010 !
b101001010 (
1%
#16600000
0%
#16625000
b101001011 !
b101001011 (
1%
#16650000
0%
#16675000
b101001100 !
b101001100 (
1%
#16700000
0%
#16725000
b101001101 !
b101001101 (
1%
#16750000
0%
#16775000
b101001110 !
b101001110 (
1%
#16800000
0%
#16825000
b101001111 !
b101001111 (
1%
#16850000
0%
#16875000
b101010000 !
b101010000 (
1%
#16900000
0%
#16925000
b101010001 !
b101010001 (
1%
#16950000
0%
#16975000
b101010010 !
b101010010 (
1%
#17000000
0%
#17025000
b101010011 !
b101010011 (
1%
#17050000
0%
#17075000
b101010100 !
b101010100 (
1%
#17100000
0%
#17125000
b101010101 !
b101010101 (
1%
#17150000
0%
#17175000
b101010110 !
b101010110 (
1%
#17200000
0%
#17225000
b101010111 !
b101010111 (
1%
#17250000
0%
#17275000
b101011000 !
b101011000 (
1%
#17300000
0%
#17325000
b101011001 !
b101011001 (
1%
#17350000
0%
#17375000
b101011010 !
b101011010 (
1%
#17400000
0%
#17425000
b101011011 !
b101011011 (
1%
#17450000
0%
#17475000
b101011100 !
b101011100 (
1%
#17500000
0%
#17525000
b101011101 !
b101011101 (
1%
#17550000
0%
#17575000
b101011110 !
b101011110 (
1%
#17600000
0%
#17625000
b101011111 !
b101011111 (
1%
#17650000
0%
#17675000
b101100000 !
b101100000 (
1%
#17700000
0%
#17725000
b101100001 !
b101100001 (
1%
#17750000
0%
#17775000
b101100010 !
b101100010 (
1%
#17800000
0%
#17825000
b101100011 !
b101100011 (
1%
#17850000
0%
#17875000
b101100100 !
b101100100 (
1%
#17900000
0%
#17925000
b101100101 !
b101100101 (
1%
#17950000
0%
#17975000
b101100110 !
b101100110 (
1%
#18000000
0%
#18025000
b101100111 !
b101100111 (
1%
#18050000
0%
#18075000
b101101000 !
b101101000 (
1%
#18100000
0%
#18125000
b101101001 !
b101101001 (
1%
#18150000
0%
#18175000
b101101010 !
b101101010 (
1%
#18200000
0%
#18225000
b101101011 !
b101101011 (
1%
#18250000
0%
#18275000
b101101100 !
b101101100 (
1%
#18300000
0%
#18325000
b101101101 !
b101101101 (
1%
#18350000
0%
#18375000
b101101110 !
b101101110 (
1%
#18400000
0%
#18425000
b101101111 !
b101101111 (
1%
#18450000
0%
#18475000
b101110000 !
b101110000 (
1%
#18500000
0%
#18525000
b101110001 !
b101110001 (
1%
#18550000
0%
#18575000
b101110010 !
b101110010 (
1%
#18600000
0%
#18625000
b101110011 !
b101110011 (
1%
#18650000
0%
#18675000
b101110100 !
b101110100 (
1%
#18700000
0%
#18725000
b101110101 !
b101110101 (
1%
#18750000
0%
#18775000
b101110110 !
b101110110 (
1%
#18800000
0%
#18825000
b101110111 !
b101110111 (
1%
#18850000
0%
#18875000
b101111000 !
b101111000 (
1%
#18900000
0%
#18925000
b101111001 !
b101111001 (
1%
#18950000
0%
#18975000
b101111010 !
b101111010 (
1%
#19000000
0%
#19025000
b101111011 !
b101111011 (
1%
#19050000
0%
#19075000
b101111100 !
b101111100 (
1%
#19100000
0%
#19125000
b101111101 !
b101111101 (
1%
#19150000
0%
#19175000
b101111110 !
b101111110 (
1%
#19200000
0%
#19225000
b101111111 !
b101111111 (
1%
#19250000
0%
#19275000
b110000000 !
b110000000 (
1%
#19300000
0%
#19325000
b110000001 !
b110000001 (
1%
#19350000
0%
#19375000
b110000010 !
b110000010 (
1%
#19400000
0%
#19425000
b110000011 !
b110000011 (
1%
#19450000
0%
#19475000
b110000100 !
b110000100 (
1%
#19500000
0%
#19525000
b110000101 !
b110000101 (
1%
#19550000
0%
#19575000
b110000110 !
b110000110 (
1%
#19600000
0%
#19625000
b110000111 !
b110000111 (
1%
#19650000
0%
#19675000
b110001000 !
b110001000 (
1%
#19700000
0%
#19725000
b110001001 !
b110001001 (
1%
#19750000
0%
#19775000
b110001010 !
b110001010 (
1%
#19800000
0%
#19825000
b110001011 !
b110001011 (
1%
#19850000
0%
#19875000
b110001100 !
b110001100 (
1%
#19900000
0%
#19925000
b110001101 !
b110001101 (
1%
#19950000
0%
#19975000
b110001110 !
b110001110 (
1%
#20000000
0%
#20025000
b110001111 !
b110001111 (
1%
#20050000
0%
#20075000
b110010000 !
b110010000 (
1%
#20100000
0%
#20125000
b110010001 !
b110010001 (
1%
#20150000
0%
#20175000
b110010010 !
b110010010 (
1%
#20200000
0%
#20225000
b110010011 !
b110010011 (
1%
#20250000
0%
#20275000
b110010100 !
b110010100 (
1%
#20300000
0%
#20325000
b110010101 !
b110010101 (
1%
#20350000
0%
#20375000
b110010110 !
b110010110 (
1%
#20400000
0%
#20425000
b110010111 !
b110010111 (
1%
#20450000
0%
#20475000
b110011000 !
b110011000 (
1%
#20500000
0%
#20525000
b110011001 !
b110011001 (
1%
#20550000
0%
#20575000
b110011010 !
b110011010 (
1%
#20600000
0%
#20625000
b110011011 !
b110011011 (
1%
#20650000
0%
#20675000
b110011100 !
b110011100 (
1%
#20700000
0%
#20725000
b110011101 !
b110011101 (
1%
#20750000
0%
#20775000
b110011110 !
b110011110 (
1%
#20800000
0%
#20825000
b110011111 !
b110011111 (
1%
#20850000
0%
#20875000
b110100000 !
b110100000 (
1%
#20900000
0%
#20925000
b110100001 !
b110100001 (
1%
#20950000
0%
#20975000
b110100010 !
b110100010 (
1%
#21000000
0%
#21025000
b110100011 !
b110100011 (
1%
#21050000
0%
#21075000
b110100100 !
b110100100 (
1%
#21100000
0%
#21125000
b110100101 !
b110100101 (
1%
#21150000
0%
#21175000
b110100110 !
b110100110 (
1%
#21200000
0%
#21225000
b110100111 !
b110100111 (
1%
#21250000
0%
#21275000
b110101000 !
b110101000 (
1%
#21300000
0%
#21325000
b110101001 !
b110101001 (
1%
#21350000
0%
#21375000
b110101010 !
b110101010 (
1%
#21400000
0%
#21425000
b110101011 !
b110101011 (
1%
#21450000
0%
#21475000
b110101100 !
b110101100 (
1%
#21500000
0%
#21525000
b110101101 !
b110101101 (
1%
#21550000
0%
#21575000
b110101110 !
b110101110 (
1%
#21600000
0%
#21625000
b110101111 !
b110101111 (
1%
#21650000
0%
#21675000
b110110000 !
b110110000 (
1%
#21700000
0%
#21725000
b110110001 !
b110110001 (
1%
#21750000
0%
#21775000
b110110010 !
b110110010 (
1%
#21800000
0%
#21825000
b110110011 !
b110110011 (
1%
#21850000
0%
#21875000
b110110100 !
b110110100 (
1%
#21900000
0%
#21925000
b110110101 !
b110110101 (
1%
#21950000
0%
#21975000
b110110110 !
b110110110 (
1%
#22000000
0%
#22025000
b110110111 !
b110110111 (
1%
#22050000
0%
#22075000
b110111000 !
b110111000 (
1%
#22100000
0%
#22125000
b110111001 !
b110111001 (
1%
#22150000
0%
#22175000
b110111010 !
b110111010 (
1%
#22200000
0%
#22225000
b110111011 !
b110111011 (
1%
#22250000
0%
#22275000
b110111100 !
b110111100 (
1%
#22300000
0%
#22325000
b110111101 !
b110111101 (
1%
#22350000
0%
#22375000
b110111110 !
b110111110 (
1%
#22400000
0%
#22425000
b110111111 !
b110111111 (
1%
#22450000
0%
#22475000
b111000000 !
b111000000 (
1%
#22500000
0%
#22525000
b111000001 !
b111000001 (
1%
#22550000
0%
#22575000
b111000010 !
b111000010 (
1%
#22600000
0%
#22625000
b111000011 !
b111000011 (
1%
#22650000
0%
#22675000
b111000100 !
b111000100 (
1%
#22700000
0%
#22725000
b111000101 !
b111000101 (
1%
#22750000
0%
#22775000
b111000110 !
b111000110 (
1%
#22800000
0%
#22825000
b111000111 !
b111000111 (
1%
#22850000
0%
#22875000
b111001000 !
b111001000 (
1%
#22900000
0%
#22925000
b111001001 !
b111001001 (
1%
#22950000
0%
#22975000
b111001010 !
b111001010 (
1%
#23000000
0%
#23025000
b111001011 !
b111001011 (
1%
#23050000
0%
#23075000
b111001100 !
b111001100 (
1%
#23100000
0%
#23125000
b111001101 !
b111001101 (
1%
#23150000
0%
#23175000
b111001110 !
b111001110 (
1%
#23200000
0%
#23225000
b111001111 !
b111001111 (
1%
#23250000
0%
#23275000
b111010000 !
b111010000 (
1%
#23300000
0%
