src/common/counter.v
// ************************************************************
// Engineer: kaikai
//
// Create Date: 2024/04/05
// Design Name: ConvCode
// Module Name: counter.v
// Tool versions: VsCode
// Description: 计数器
// Parameter:
// 1. NUM: 计数器的最大值
// 2. LEN: 计数器的长度
// Input:
// 1. clk_sig: 时钟信号
// 2. reset_sig: 复位信号
// Output:
// 1. counter_sig: 计数器的值
// ************************************************************
module counter #(
    parameter NUM = 11'b111_1111_1111
) (
    input                            clk_sig,
    input                            reset_sig,   // 复位信号 低电平有效
    output reg [($clog2(NUM) - 1):0] counter_sig  // 计数器的值
);
    initial begin
        counter_sig <= 0;
    end

    always @(posedge clk_sig) begin
        if (!reset_sig || counter_sig == NUM) begin
            counter_sig <= 0;
        end else begin
            counter_sig <= counter_sig + 1;
        end
    end
endmodule

src/common/div.v
// ************************************************************
// Engineer: kaikai
//
// Create Date: 2024/04/05
// Design Name: ConvCode
// Module Name: div.v
// Tool versions: VsCode
// Description: 分频器
// Parameter:
// 1. NUM: 分频数
// 2. DUTY: 占空比
// Input:
// 1. clk_sig: 时钟信号
// 2. rst_sig: 复位信号
// Output:
// 1. div_sig: 分频后的信号
// ************************************************************
module div #(
    parameter NUM  = 4,  // 分频数
    parameter DUTY = 2   // 占空比: 2/4 = 50%
) (
    input  wire clk_sig,
    input  wire rst_sig,
    output reg  div_sig
);
    wire [($clog2(NUM) - 1):0] counter_sig;
    counter #(
        .NUM(NUM - 1)
    ) counter_inst (
        .clk_sig    (clk_sig),
        .reset_sig  (rst_sig),
        .counter_sig(counter_sig)
    );

    always @(posedge clk_sig)
        if (!rst_sig) div_sig <= 0;
        else if (counter_sig < DUTY)  // 4 分频 * 50% 占空比
            div_sig <= 1;
        else div_sig <= 0;
endmodule

test/div_tb.v
//~ `New testbench
`timescale 1ns / 1ps

module div_tb;

    // div Parameters
    parameter PERIOD = 50;
    parameter NUM = 4;
    parameter DUTY = 2;

    /*iverilog */
    initial begin
        $dumpfile("div.vcd");  //生成的vcd文件名称
        $dumpvars(0, div_tb);  //tb模块名称
    end
    /*iverilog */

    // div Inputs
    reg  clk_sig = 0;
    reg  rst_sig = 0;

    // div Outputs
    wire div_sig;

    always begin
        #(PERIOD / 2) clk_sig = ~clk_sig;
    end

    initial begin
        #(PERIOD * 2) rst_sig = 1;
    end

    div #(
        .NUM (NUM),
        .DUTY(DUTY)
    ) u_div (
        .clk_sig(clk_sig),
        .rst_sig(rst_sig),

        .div_sig(div_sig)
    );

    initial begin
        #10000 $finish;
    end

endmodule

div.vcd
$date
	Fri Apr  5 23:34:02 2024
$end
$version
	Icarus Verilog
$end
$timescale
	1ps
$end
$scope module div_tb $end
$var wire 1 ! div_sig $end
$var parameter 32 " DUTY $end
$var parameter 32 # NUM $end
$var parameter 32 $ PERIOD $end
$var reg 1 % clk_sig $end
$var reg 1 & rst_sig $end
$scope module u_div $end
$var wire 1 % clk_sig $end
$var wire 1 & rst_sig $end
$var wire 2 ' counter_sig [1:0] $end
$var parameter 32 ( DUTY $end
$var parameter 32 ) NUM $end
$var reg 1 ! div_sig $end
$scope module counter_inst $end
$var wire 1 % clk_sig $end
$var wire 1 & reset_sig $end
$var parameter 33 * NUM $end
$var reg 2 + counter_sig [1:0] $end
$upscope $end
$upscope $end
$upscope $end
$enddefinitions $end
$comment Show the parameter values. $end
$dumpall
b11 *
b100 )
b10 (
b110010 $
b100 #
b10 "
$end
#0
$dumpvars
b0 +
b0 '
0&
0%
x!
$end
#25000
0!
1%
#50000
0%
#75000
1%
#100000
0%
1&
#125000
b1 '
b1 +
1!
1%
#150000
0%
#175000
b10 '
b10 +
1%
#200000
0%
#225000
b11 '
b11 +
0!
1%
#250000
0%
#275000
b0 '
b0 +
1%
#300000
0%
#325000
b1 '
b1 +
1!
1%
#350000
0%
#375000
b10 '
b10 +
1%
#400000
0%
#425000
b11 '
b11 +
0!
1%
#450000
0%
#475000
b0 '
b0 +
1%
#500000
0%
#525000
b1 '
b1 +
1!
1%
#550000
0%
#575000
b10 '
b10 +
1%
#600000
0%
#625000
b11 '
b11 +
0!
1%
#650000
0%
#675000
b0 '
b0 +
1%
#700000
0%
#725000
b1 '
b1 +
1!
1%
#750000
0%
#775000
b10 '
b10 +
1%
#800000
0%
#825000
b11 '
b11 +
0!
1%
#850000
0%
#875000
b0 '
b0 +
1%
#900000
0%
#925000
b1 '
b1 +
1!
1%
#950000
0%
#975000
b10 '
b10 +
1%
#1000000
0%
#1025000
b11 '
b11 +
0!
1%
#1050000
0%
#1075000
b0 '
b0 +
1%
#1100000
0%
#1125000
b1 '
b1 +
1!
1%
#1150000
0%
#1175000
b10 '
b10 +
1%
#1200000
0%
#1225000
b11 '
b11 +
0!
1%
#1250000
0%
#1275000
b0 '
b0 +
1%
#1300000
0%
#1325000
b1 '
b1 +
1!
1%
#1350000
0%
#1375000
b10 '
b10 +
1%
#1400000
0%
#1425000
b11 '
b11 +
0!
1%
#1450000
0%
#1475000
b0 '
b0 +
1%
#1500000
0%
#1525000
b1 '
b1 +
1!
1%
#1550000
0%
#1575000
b10 '
b10 +
1%
#1600000
0%
#1625000
b11 '
b11 +
0!
1%
#1650000
0%
#1675000
b0 '
b0 +
1%
#1700000
0%
#1725000
b1 '
b1 +
1!
1%
#1750000
0%
#1775000
b10 '
b10 +
1%
#1800000
0%
#1825000
b11 '
b11 +
0!
1%
#1850000
0%
#1875000
b0 '
b0 +
1%
#1900000
0%
#1925000
b1 '
b1 +
1!
1%
#1950000
0%
#1975000
b10 '
b10 +
1%
#2000000
0%
#2025000
b11 '
b11 +
0!
1%
#2050000
0%
#2075000
b0 '
b0 +
1%
#2100000
0%
#2125000
b1 '
b1 +
1!
1%
#2150000
0%
#2175000
b10 '
b10 +
1%
#2200000
0%
#2225000
b11 '
b11 +
0!
1%
#2250000
0%
#2275000
b0 '
b0 +
1%
#2300000
0%
#2325000
b1 '
b1 +
1!
1%
#2350000
0%
#2375000
b10 '
b10 +
1%
#2400000
0%
#2425000
b11 '
b11 +
0!
1%
#2450000
0%
#2475000
b0 '
b0 +
1%
#2500000
0%
#2525000
b1 '
b1 +
1!
1%
#2550000
0%
#2575000
b10 '
b10 +
1%
#2600000
0%
#2625000
b11 '
b11 +
0!
1%
#2650000
0%
#2675000
b0 '
b0 +
1%
#2700000
0%
#2725000
b1 '
b1 +
1!
1%
#2750000
0%
#2775000
b10 '
b10 +
1%
#2800000
0%
#2825000
b11 '
b11 +
0!
1%
#2850000
0%
#2875000
b0 '
b0 +
1%
#2900000
0%
#2925000
b1 '
b1 +
1!
1%
#2950000
0%
#2975000
b10 '
b10 +
1%
#3000000
0%
#3025000
b11 '
b11 +
0!
1%
#3050000
0%
#3075000
b0 '
b0 +
1%
#3100000
0%
#3125000
b1 '
b1 +
1!
1%
#3150000
0%
#3175000
b10 '
b10 +
1%
#3200000
0%
#3225000
b11 '
b11 +
0!
1%
#3250000
0%
#3275000
b0 '
b0 +
1%
#3300000
0%
#3325000
b1 '
b1 +
1!
1%
#3350000
0%
#3375000
b10 '
b10 +
1%
#3400000
0%
#3425000
b11 '
b11 +
0!
1%
#3450000
0%
#3475000
b0 '
b0 +
1%
#3500000
0%
#3525000
b1 '
b1 +
1!
1%
#3550000
0%
#3575000
b10 '
b10 +
1%
#3600000
0%
#3625000
b11 '
b11 +
0!
1%
#3650000
0%
#3675000
b0 '
b0 +
1%
#3700000
0%
#3725000
b1 '
b1 +
1!
1%
#3750000
0%
#3775000
b10 '
b10 +
1%
#3800000
0%
#3825000
b11 '
b11 +
0!
1%
#3850000
0%
#3875000
b0 '
b0 +
1%
#3900000
0%
#3925000
b1 '
b1 +
1!
1%
#3950000
0%
#3975000
b10 '
b10 +
1%
#4000000
0%
#4025000
b11 '
b11 +
0!
1%
#4050000
0%
#4075000
b0 '
b0 +
1%
#4100000
0%
#4125000
b1 '
b1 +
1!
1%
#4150000
0%
#4175000
b10 '
b10 +
1%
#4200000
0%
#4225000
b11 '
b11 +
0!
1%
#4250000
0%
#4275000
b0 '
b0 +
1%
#4300000
0%
#4325000
b1 '
b1 +
1!
1%
#4350000
0%
#4375000
b10 '
b10 +
1%
#4400000
0%
#4425000
b11 '
b11 +
0!
1%
#4450000
0%
#4475000
b0 '
b0 +
1%
#4500000
0%
#4525000
b1 '
b1 +
1!
1%
#4550000
0%
#4575000
b10 '
b10 +
1%
#4600000
0%
#4625000
b11 '
b11 +
0!
1%
#4650000
0%
#4675000
b0 '
b0 +
1%
#4700000
0%
#4725000
b1 '
b1 +
1!
1%
#4750000
0%
#4775000
b10 '
b10 +
1%
#4800000
0%
#4825000
b11 '
b11 +
0!
1%
#4850000
0%
#4875000
b0 '
b0 +
1%
#4900000
0%
#4925000
b1 '
b1 +
1!
1%
#4950000
0%
#4975000
b10 '
b10 +
1%
#5000000
0%
#5025000
b11 '
b11 +
0!
1%
#5050000
0%
#5075000
b0 '
b0 +
1%
#5100000
0%
#5125000
b1 '
b1 +
1!
1%
#5150000
0%
#5175000
b10 '
b10 +
1%
#5200000
0%
#5225000
b11 '
b11 +
0!
1%
#5250000
0%
#5275000
b0 '
b0 +
1%
#5300000
0%
#5325000
b1 '
b1 +
1!
1%
#5350000
0%
#5375000
b10 '
b10 +
1%
#5400000
0%
#5425000
b11 '
b11 +
0!
1%
#5450000
0%
#5475000
b0 '
b0 +
1%
#5500000
0%
#5525000
b1 '
b1 +
1!
1%
#5550000
0%
#5575000
b10 '
b10 +
1%
#5600000
0%
#5625000
b11 '
b11 +
0!
1%
#5650000
0%
#5675000
b0 '
b0 +
1%
#5700000
0%
#5725000
b1 '
b1 +
1!
1%
#5750000
0%
#5775000
b10 '
b10 +
1%
#5800000
0%
#5825000
b11 '
b11 +
0!
1%
#5850000
0%
#5875000
b0 '
b0 +
1%
#5900000
0%
#5925000
b1 '
b1 +
1!
1%
#5950000
0%
#5975000
b10 '
b10 +
1%
#6000000
0%
#6025000
b11 '
b11 +
0!
1%
#6050000
0%
#6075000
b0 '
b0 +
1%
#6100000
0%
#6125000
b1 '
b1 +
1!
1%
#6150000
0%
#6175000
b10 '
b10 +
1%
#6200000
0%
#6225000
b11 '
b11 +
0!
1%
#6250000
0%
#6275000
b0 '
b0 +
1%
#6300000
0%
#6325000
b1 '
b1 +
1!
1%
#6350000
0%
#6375000
b10 '
b10 +
1%
#6400000
0%
#6425000
b11 '
b11 +
0!
1%
#6450000
0%
#6475000
b0 '
b0 +
1%
#6500000
0%
#6525000
b1 '
b1 +
1!
1%
#6550000
0%
#6575000
b10 '
b10 +
1%
#6600000
0%
#6625000
b11 '
b11 +
0!
1%
#6650000
0%
#6675000
b0 '
b0 +
1%
#6700000
0%
#6725000
b1 '
b1 +
1!
1%
#6750000
0%
#6775000
b10 '
b10 +
1%
#6800000
0%
#6825000
b11 '
b11 +
0!
1%
#6850000
0%
#6875000
b0 '
b0 +
1%
#6900000
0%
#6925000
b1 '
b1 +
1!
1%
#6950000
0%
#6975000
b10 '
b10 +
1%
#7000000
0%
#7025000
b11 '
b11 +
0!
1%
#7050000
0%
#7075000
b0 '
b0 +
1%
#7100000
0%
#7125000
b1 '
b1 +
1!
1%
#7150000
0%
#7175000
b10 '
b10 +
1%
#7200000
0%
#7225000
b11 '
b11 +
0!
1%
#7250000
0%
#7275000
b0 '
b0 +
1%
#7300000
0%
#7325000
b1 '
b1 +
1!
1%
#7350000
0%
#7375000
b10 '
b10 +
1%
#7400000
0%
#7425000
b11 '
b11 +
0!
1%
#7450000
0%
#7475000
b0 '
b0 +
1%
#7500000
0%
#7525000
b1 '
b1 +
1!
1%
#7550000
0%
#7575000
b10 '
b10 +
1%
#7600000
0%
#7625000
b11 '
b11 +
0!
1%
#7650000
0%
#7675000
b0 '
b0 +
1%
#7700000
0%
#7725000
b1 '
b1 +
1!
1%
#7750000
0%
#7775000
b10 '
b10 +
1%
#7800000
0%
#7825000
b11 '
b11 +
0!
1%
#7850000
0%
#7875000
b0 '
b0 +
1%
#7900000
0%
#7925000
b1 '
b1 +
1!
1%
#7950000
0%
#7975000
b10 '
b10 +
1%
#8000000
0%
#8025000
b11 '
b11 +
0!
1%
#8050000
0%
#8075000
b0 '
b0 +
1%
#8100000
0%
#8125000
b1 '
b1 +
1!
1%
#8150000
0%
#8175000
b10 '
b10 +
1%
#8200000
0%
#8225000
b11 '
b11 +
0!
1%
#8250000
0%
#8275000
b0 '
b0 +
1%
#8300000
0%
#8325000
b1 '
b1 +
1!
1%
#8350000
0%
#8375000
b10 '
b10 +
1%
#8400000
0%
#8425000
b11 '
b11 +
0!
1%
#8450000
0%
#8475000
b0 '
b0 +
1%
#8500000
0%
#8525000
b1 '
b1 +
1!
1%
#8550000
0%
#8575000
b10 '
b10 +
1%
#8600000
0%
#8625000
b11 '
b11 +
0!
1%
#8650000
0%
#8675000
b0 '
b0 +
1%
#8700000
0%
#8725000
b1 '
b1 +
1!
1%
#8750000
0%
#8775000
b10 '
b10 +
1%
#8800000
0%
#8825000
b11 '
b11 +
0!
1%
#8850000
0%
#8875000
b0 '
b0 +
1%
#8900000
0%
#8925000
b1 '
b1 +
1!
1%
#8950000
0%
#8975000
b10 '
b10 +
1%
#9000000
0%
#9025000
b11 '
b11 +
0!
1%
#9050000
0%
#9075000
b0 '
b0 +
1%
#9100000
0%
#9125000
b1 '
b1 +
1!
1%
#9150000
0%
#9175000
b10 '
b10 +
1%
#9200000
0%
#9225000
b11 '
b11 +
0!
1%
#9250000
0%
#9275000
b0 '
b0 +
1%
#9300000
0%
#9325000
b1 '
b1 +
1!
1%
#9350000
0%
#9375000
b10 '
b10 +
1%
#9400000
0%
#9425000
b11 '
b11 +
0!
1%
#9450000
0%
#9475000
b0 '
b0 +
1%
#9500000
0%
#9525000
b1 '
b1 +
1!
1%
#9550000
0%
#9575000
b10 '
b10 +
1%
#9600000
0%
#9625000
b11 '
b11 +
0!
1%
#9650000
0%
#9675000
b0 '
b0 +
1%
#9700000
0%
#9725000
b1 '
b1 +
1!
1%
#9750000
0%
#9775000
b10 '
b10 +
1%
#9800000
0%
#9825000
b11 '
b11 +
0!
1%
#9850000
0%
#9875000
b0 '
b0 +
1%
#9900000
0%
#9925000
b1 '
b1 +
1!
1%
#9950000
0%
#9975000
b10 '
b10 +
1%
