src/common/mseries.v
// ************************************************************
// Engineer: kaikai
//
// Create Date: 2024/04/06
// Design Name: ConvCode
// Module Name: mseries.v
// Tool versions: VsCode
// Description: M 序列发生器
// Parameter:
// 1. M: M 序列的阶数 2-16
// Input:
// 1. clk_sig: 时钟信号
// 2. reset_sig: 复位信号
// Output:
// 1. m_sig: M 序列
// ************************************************************
module mseries #(
    parameter M = 4  // parameter range from 2 to 16
) (
    input  wire clk_sig,
    input  wire rst_sig,
    output wire m_sig
);

    reg [(M-1):0] m_r;

    initial begin
        m_r = ~(0);
    end

    always @(posedge clk_sig) begin
        if (rst_sig == 0) begin  // negedge reset
            m_r <= ~(0);
        end else begin
            m_r <= m_r << 1;  // shift reg
            case (M)
                2: m_r[0] <= m_r[1] ^ m_r[0];
                3: m_r[0] <= m_r[2] ^ m_r[1];
                4: m_r[0] <= m_r[3] ^ m_r[2];
                5: m_r[0] <= m_r[4] ^ m_r[2];
                6: m_r[0] <= m_r[5] ^ m_r[4];
                7: m_r[0] <= m_r[6] ^ m_r[3];
                8: m_r[0] <= m_r[7] ^ m_r[5] ^ m_r[4] ^ m_r[3];
                9: m_r[0] <= m_r[8] ^ m_r[4];
                10: m_r[0] <= m_r[9] ^ m_r[6];
                11: m_r[0] <= m_r[10] ^ m_r[8];
                12: m_r[0] <= m_r[11] ^ m_r[10] ^ m_r[7] ^ m_r[5];
                13: m_r[0] <= m_r[12] ^ m_r[11] ^ m_r[9] ^ m_r[8];
                14: m_r[0] <= m_r[13] ^ m_r[12] ^ m_r[7] ^ m_r[3];
                15: m_r[0] <= m_r[14] ^ m_r[13];
                16: m_r[0] <= m_r[15] ^ m_r[14] ^ m_r[12] ^ m_r[3];
                default: m_r[0] <= m_r[0];
            endcase
        end
    end

    assign m_sig = m_r[(M-1)];
endmodule

test/mseries_tb.v
//~ `New testbench
`timescale 1ns / 1ps

module mseries_tb;

    // mseries Parameters
    parameter PERIOD = 50;
    parameter M = 16;

    // mseries Inputs
    reg  clk_sig = 0;
    reg  rst_sig = 0;

    // mseries Outputs
    wire m_sig;

    /*iverilog */
    initial begin
        $dumpfile("mseries.vcd");  //生成的vcd文件名称
        $dumpvars(0, mseries_tb);  //tb模块名称
    end
    /*iverilog */

    always begin
        #(PERIOD / 2) clk_sig = ~clk_sig;
    end

    initial begin
        #(PERIOD * 2) rst_sig = 1;
    end

    mseries #(
        .M(M)
    ) u_mseries (
        .clk_sig(clk_sig),
        .rst_sig(rst_sig),

        .m_sig(m_sig)
    );

    initial begin
        #10000 $finish;
    end

endmodule

mseries.vcd
$date
	Sat Apr  6 14:56:18 2024
$end
$version
	Icarus Verilog
$end
$timescale
	1ps
$end
$scope module mseries_tb $end
$var wire 1 ! m_sig $end
$var parameter 32 " M $end
$var parameter 32 # PERIOD $end
$var reg 1 $ clk_sig $end
$var reg 1 % rst_sig $end
$scope module u_mseries $end
$var wire 1 $ clk_sig $end
$var wire 1 % rst_sig $end
$var wire 1 ! m_sig $end
$var parameter 32 & M $end
$var reg 16 ' m_r [15:0] $end
$upscope $end
$upscope $end
$enddefinitions $end
$comment Show the parameter values. $end
$dumpall
b10000 &
b110010 #
b10000 "
$end
#0
$dumpvars
b1111111111111111 '
0%
0$
1!
$end
#25000
1$
#50000
0$
#75000
1$
#100000
0$
1%
#125000
b1111111111111110 '
1$
#150000
0$
#175000
b1111111111111100 '
1$
#200000
0$
#225000
b1111111111111000 '
1$
#250000
0$
#275000
b1111111111110000 '
1$
#300000
0$
#325000
b1111111111100001 '
1$
#350000
0$
#375000
b1111111111000011 '
1$
#400000
0$
#425000
b1111111110000111 '
1$
#450000
0$
#475000
b1111111100001111 '
1$
#500000
0$
#525000
b1111111000011110 '
1$
#550000
0$
#575000
b1111110000111100 '
1$
#600000
0$
#625000
b1111100001111000 '
1$
#650000
0$
#675000
b1111000011110000 '
1$
#700000
0$
#725000
b1110000111100001 '
1$
#750000
0$
#775000
b1100001111000010 '
1$
#800000
0$
#825000
b1000011110000100 '
1$
#850000
0$
#875000
0!
b111100001001 '
1$
#900000
0$
#925000
b1111000010011 '
1$
#950000
0$
#975000
b11110000100111 '
1$
#1000000
0$
#1025000
b111100001001111 '
1$
#1050000
0$
#1075000
1!
b1111000010011111 '
1$
#1100000
0$
#1125000
b1110000100111110 '
1$
#1150000
0$
#1175000
b1100001001111101 '
1$
#1200000
0$
#1225000
b1000010011111011 '
1$
#1250000
0$
#1275000
0!
b100111110110 '
1$
#1300000
0$
#1325000
b1001111101100 '
1$
#1350000
0$
#1375000
b10011111011000 '
1$
#1400000
0$
#1425000
b100111110110001 '
1$
#1450000
0$
#1475000
1!
b1001111101100011 '
1$
#1500000
0$
#1525000
0!
b11111011000110 '
1$
#1550000
0$
#1575000
b111110110001101 '
1$
#1600000
0$
#1625000
1!
b1111101100011011 '
1$
#1650000
0$
#1675000
b1111011000110110 '
1$
#1700000
0$
#1725000
b1110110001101101 '
1$
#1750000
0$
#1775000
b1101100011011011 '
1$
#1800000
0$
#1825000
b1011000110110110 '
1$
#1850000
0$
#1875000
0!
b110001101101100 '
1$
#1900000
0$
#1925000
1!
b1100011011011000 '
1$
#1950000
0$
#1975000
b1000110110110001 '
1$
#2000000
0$
#2025000
0!
b1101101100011 '
1$
#2050000
0$
#2075000
b11011011000111 '
1$
#2100000
0$
#2125000
b110110110001111 '
1$
#2150000
0$
#2175000
1!
b1101101100011110 '
1$
#2200000
0$
#2225000
b1011011000111100 '
1$
#2250000
0$
#2275000
0!
b110110001111001 '
1$
#2300000
0$
#2325000
1!
b1101100011110010 '
1$
#2350000
0$
#2375000
b1011000111100101 '
1$
#2400000
0$
#2425000
0!
b110001111001010 '
1$
#2450000
0$
#2475000
1!
b1100011110010100 '
1$
#2500000
0$
#2525000
b1000111100101000 '
1$
#2550000
0$
#2575000
0!
b1111001010000 '
1$
#2600000
0$
#2625000
b11110010100001 '
1$
#2650000
0$
#2675000
b111100101000011 '
1$
#2700000
0$
#2725000
1!
b1111001010000110 '
1$
#2750000
0$
#2775000
b1110010100001101 '
1$
#2800000
0$
#2825000
b1100101000011011 '
1$
#2850000
0$
#2875000
b1001010000110111 '
1$
#2900000
0$
#2925000
0!
b10100001101110 '
1$
#2950000
0$
#2975000
b101000011011101 '
1$
#3000000
0$
#3025000
1!
b1010000110111011 '
1$
#3050000
0$
#3075000
0!
b100001101110110 '
1$
#3100000
0$
#3125000
1!
b1000011011101101 '
1$
#3150000
0$
#3175000
0!
b110111011010 '
1$
#3200000
0$
#3225000
b1101110110101 '
1$
#3250000
0$
#3275000
b11011101101011 '
1$
#3300000
0$
#3325000
b110111011010110 '
1$
#3350000
0$
#3375000
1!
b1101110110101101 '
1$
#3400000
0$
#3425000
b1011101101011010 '
1$
#3450000
0$
#3475000
0!
b111011010110101 '
1$
#3500000
0$
#3525000
1!
b1110110101101010 '
1$
#3550000
0$
#3575000
b1101101011010101 '
1$
#3600000
0$
#3625000
b1011010110101011 '
1$
#3650000
0$
#3675000
0!
b110101101010111 '
1$
#3700000
0$
#3725000
1!
b1101011010101111 '
1$
#3750000
0$
#3775000
b1010110101011110 '
1$
#3800000
0$
#3825000
0!
b101101010111100 '
1$
#3850000
0$
#3875000
1!
b1011010101111001 '
1$
#3900000
0$
#3925000
0!
b110101011110011 '
1$
#3950000
0$
#3975000
1!
b1101010111100111 '
1$
#4000000
0$
#4025000
b1010101111001111 '
1$
#4050000
0$
#4075000
0!
b101011110011110 '
1$
#4100000
0$
#4125000
1!
b1010111100111101 '
1$
#4150000
0$
#4175000
0!
b101111001111010 '
1$
#4200000
0$
#4225000
1!
b1011110011110101 '
1$
#4250000
0$
#4275000
0!
b111100111101010 '
1$
#4300000
0$
#4325000
1!
b1111001111010101 '
1$
#4350000
0$
#4375000
b1110011110101011 '
1$
#4400000
0$
#4425000
b1100111101010111 '
1$
#4450000
0$
#4475000
b1001111010101110 '
1$
#4500000
0$
#4525000
0!
b11110101011101 '
1$
#4550000
0$
#4575000
b111101010111010 '
1$
#4600000
0$
#4625000
1!
b1111010101110101 '
1$
#4650000
0$
#4675000
b1110101011101011 '
1$
#4700000
0$
#4725000
b1101010111010111 '
1$
#4750000
0$
#4775000
b1010101110101111 '
1$
#4800000
0$
#4825000
0!
b101011101011110 '
1$
#4850000
0$
#4875000
1!
b1010111010111101 '
1$
#4900000
0$
#4925000
0!
b101110101111010 '
1$
#4950000
0$
#4975000
1!
b1011101011110101 '
1$
#5000000
0$
#5025000
0!
b111010111101010 '
1$
#5050000
0$
#5075000
1!
b1110101111010101 '
1$
#5100000
0$
#5125000
b1101011110101010 '
1$
#5150000
0$
#5175000
b1010111101010100 '
1$
#5200000
0$
#5225000
0!
b101111010101001 '
1$
#5250000
0$
#5275000
1!
b1011110101010011 '
1$
#5300000
0$
#5325000
0!
b111101010100110 '
1$
#5350000
0$
#5375000
1!
b1111010101001100 '
1$
#5400000
0$
#5425000
b1110101010011000 '
1$
#5450000
0$
#5475000
b1101010100110001 '
1$
#5500000
0$
#5525000
b1010101001100011 '
1$
#5550000
0$
#5575000
0!
b101010011000111 '
1$
#5600000
0$
#5625000
1!
b1010100110001110 '
1$
#5650000
0$
#5675000
0!
b101001100011100 '
1$
#5700000
0$
#5725000
1!
b1010011000111001 '
1$
#5750000
0$
#5775000
0!
b100110001110010 '
1$
#5800000
0$
#5825000
1!
b1001100011100101 '
1$
#5850000
0$
#5875000
0!
b11000111001010 '
1$
#5900000
0$
#5925000
b110001110010100 '
1$
#5950000
0$
#5975000
1!
b1100011100101001 '
1$
#6000000
0$
#6025000
b1000111001010011 '
1$
#6050000
0$
#6075000
0!
b1110010100111 '
1$
#6100000
0$
#6125000
b11100101001111 '
1$
#6150000
0$
#6175000
b111001010011110 '
1$
#6200000
0$
#6225000
1!
b1110010100111101 '
1$
#6250000
0$
#6275000
b1100101001111011 '
1$
#6300000
0$
#6325000
b1001010011110111 '
1$
#6350000
0$
#6375000
0!
b10100111101110 '
1$
#6400000
0$
#6425000
b101001111011101 '
1$
#6450000
0$
#6475000
1!
b1010011110111011 '
1$
#6500000
0$
#6525000
0!
b100111101110110 '
1$
#6550000
0$
#6575000
1!
b1001111011101101 '
1$
#6600000
0$
#6625000
0!
b11110111011011 '
1$
#6650000
0$
#6675000
b111101110110110 '
1$
#6700000
0$
#6725000
1!
b1111011101101100 '
1$
#6750000
0$
#6775000
b1110111011011000 '
1$
#6800000
0$
#6825000
b1101110110110001 '
1$
#6850000
0$
#6875000
b1011101101100011 '
1$
#6900000
0$
#6925000
0!
b111011011000110 '
1$
#6950000
0$
#6975000
1!
b1110110110001100 '
1$
#7000000
0$
#7025000
b1101101100011001 '
1$
#7050000
0$
#7075000
b1011011000110010 '
1$
#7100000
0$
#7125000
0!
b110110001100100 '
1$
#7150000
0$
#7175000
1!
b1101100011001001 '
1$
#7200000
0$
#7225000
b1011000110010010 '
1$
#7250000
0$
#7275000
0!
b110001100100100 '
1$
#7300000
0$
#7325000
1!
b1100011001001001 '
1$
#7350000
0$
#7375000
b1000110010010011 '
1$
#7400000
0$
#7425000
0!
b1100100100111 '
1$
#7450000
0$
#7475000
b11001001001111 '
1$
#7500000
0$
#7525000
b110010010011110 '
1$
#7550000
0$
#7575000
1!
b1100100100111100 '
1$
#7600000
0$
#7625000
b1001001001111001 '
1$
#7650000
0$
#7675000
0!
b10010011110011 '
1$
#7700000
0$
#7725000
b100100111100110 '
1$
#7750000
0$
#7775000
1!
b1001001111001101 '
1$
#7800000
0$
#7825000
0!
b10011110011011 '
1$
#7850000
0$
#7875000
b100111100110111 '
1$
#7900000
0$
#7925000
1!
b1001111001101111 '
1$
#7950000
0$
#7975000
0!
b11110011011111 '
1$
#8000000
0$
#8025000
b111100110111110 '
1$
#8050000
0$
#8075000
1!
b1111001101111101 '
1$
#8100000
0$
#8125000
b1110011011111010 '
1$
#8150000
0$
#8175000
b1100110111110101 '
1$
#8200000
0$
#8225000
b1001101111101010 '
1$
#8250000
0$
#8275000
0!
b11011111010101 '
1$
#8300000
0$
#8325000
b110111110101011 '
1$
#8350000
0$
#8375000
1!
b1101111101010110 '
1$
#8400000
0$
#8425000
b1011111010101101 '
1$
#8450000
0$
#8475000
0!
b111110101011011 '
1$
#8500000
0$
#8525000
1!
b1111101010110111 '
1$
#8550000
0$
#8575000
b1111010101101111 '
1$
#8600000
0$
#8625000
b1110101011011110 '
1$
#8650000
0$
#8675000
b1101010110111101 '
1$
#8700000
0$
#8725000
b1010101101111010 '
1$
#8750000
0$
#8775000
0!
b101011011110100 '
1$
#8800000
0$
#8825000
1!
b1010110111101000 '
1$
#8850000
0$
#8875000
0!
b101101111010000 '
1$
#8900000
0$
#8925000
1!
b1011011110100000 '
1$
#8950000
0$
#8975000
0!
b110111101000000 '
1$
#9000000
0$
#9025000
1!
b1101111010000001 '
1$
#9050000
0$
#9075000
b1011110100000011 '
1$
#9100000
0$
#9125000
0!
b111101000000110 '
1$
#9150000
0$
#9175000
1!
b1111010000001100 '
1$
#9200000
0$
#9225000
b1110100000011000 '
1$
#9250000
0$
#9275000
b1101000000110001 '
1$
#9300000
0$
#9325000
b1010000001100011 '
1$
#9350000
0$
#9375000
0!
b100000011000111 '
1$
#9400000
0$
#9425000
1!
b1000000110001111 '
1$
#9450000
0$
#9475000
0!
b1100011110 '
1$
#9500000
0$
#9525000
b11000111101 '
1$
#9550000
0$
#9575000
b110001111011 '
1$
#9600000
0$
#9625000
b1100011110111 '
1$
#9650000
0$
#9675000
b11000111101111 '
1$
#9700000
0$
#9725000
b110001111011110 '
1$
#9750000
0$
#9775000
1!
b1100011110111100 '
1$
#9800000
0$
#9825000
b1000111101111001 '
1$
#9850000
0$
#9875000
0!
b1111011110010 '
1$
#9900000
0$
#9925000
b11110111100101 '
1$
#9950000
0$
#9975000
b111101111001011 '
1$
